<annotation>
	<folder>imagesRaw</folder>
	<filename>2017-12-22 15:05:40.586975.jpg</filename>
	<path>/Users/abell/Development/other.nyc/Camera/imagesRaw/2017-12-22 15:05:40.586975.jpg</path>
	<source>
		<database>Unknown</database>
	</source>
	<size>
		<width>352</width>
		<height>240</height>
		<depth>3</depth>
	</size>
	<segmented>0</segmented>
	<object>
		<name>car</name>
		<pose>Unspecified</pose>
		<truncated>0</truncated>
		<difficult>0</difficult>
		<bndbox>
			<xmin>154</xmin>
			<ymin>150</ymin>
			<xmax>175</xmax>
			<ymax>164</ymax>
		</bndbox>
	</object>
	<object>
		<name>police</name>
		<pose>Unspecified</pose>
		<truncated>0</truncated>
		<difficult>0</difficult>
		<bndbox>
			<xmin>97</xmin>
			<ymin>161</ymin>
			<xmax>126</xmax>
			<ymax>186</ymax>
		</bndbox>
	</object>
	<object>
		<name>car</name>
		<pose>Unspecified</pose>
		<truncated>0</truncated>
		<difficult>0</difficult>
		<bndbox>
			<xmin>72</xmin>
			<ymin>159</ymin>
			<xmax>99</xmax>
			<ymax>175</ymax>
		</bndbox>
	</object>
	<object>
		<name>car</name>
		<pose>Unspecified</pose>
		<truncated>0</truncated>
		<difficult>0</difficult>
		<bndbox>
			<xmin>151</xmin>
			<ymin>140</ymin>
			<xmax>169</xmax>
			<ymax>155</ymax>
		</bndbox>
	</object>
	<object>
		<name>car</name>
		<pose>Unspecified</pose>
		<truncated>0</truncated>
		<difficult>0</difficult>
		<bndbox>
			<xmin>201</xmin>
			<ymin>148</ymin>
			<xmax>218</xmax>
			<ymax>162</ymax>
		</bndbox>
	</object>
	<object>
		<name>pedestrian</name>
		<pose>Unspecified</pose>
		<truncated>0</truncated>
		<difficult>0</difficult>
		<bndbox>
			<xmin>328</xmin>
			<ymin>188</ymin>
			<xmax>342</xmax>
			<ymax>223</ymax>
		</bndbox>
	</object>
	<object>
		<name>pedestrian</name>
		<pose>Unspecified</pose>
		<truncated>0</truncated>
		<difficult>0</difficult>
		<bndbox>
			<xmin>251</xmin>
			<ymin>151</ymin>
			<xmax>261</xmax>
			<ymax>172</ymax>
		</bndbox>
	</object>
</annotation>
