<annotation>
	<folder>imagesRaw</folder>
	<filename>2017-12-16 14:22:24.943931.jpg</filename>
	<path>/Users/abell/Development/other.nyc/Camera/imagesRaw/2017-12-16 14:22:24.943931.jpg</path>
	<source>
		<database>Unknown</database>
	</source>
	<size>
		<width>352</width>
		<height>240</height>
		<depth>3</depth>
	</size>
	<segmented>0</segmented>
	<object>
		<name>bus</name>
		<pose>Unspecified</pose>
		<truncated>0</truncated>
		<difficult>0</difficult>
		<bndbox>
			<xmin>163</xmin>
			<ymin>140</ymin>
			<xmax>235</xmax>
			<ymax>208</ymax>
		</bndbox>
	</object>
	<object>
		<name>police</name>
		<pose>Unspecified</pose>
		<truncated>0</truncated>
		<difficult>0</difficult>
		<bndbox>
			<xmin>218</xmin>
			<ymin>183</ymin>
			<xmax>276</xmax>
			<ymax>235</ymax>
		</bndbox>
	</object>
	<object>
		<name>car</name>
		<pose>Unspecified</pose>
		<truncated>0</truncated>
		<difficult>0</difficult>
		<bndbox>
			<xmin>180</xmin>
			<ymin>124</ymin>
			<xmax>189</xmax>
			<ymax>134</ymax>
		</bndbox>
	</object>
	<object>
		<name>car</name>
		<pose>Unspecified</pose>
		<truncated>1</truncated>
		<difficult>0</difficult>
		<bndbox>
			<xmin>75</xmin>
			<ymin>212</ymin>
			<xmax>132</xmax>
			<ymax>240</ymax>
		</bndbox>
	</object>
	<object>
		<name>pedestrian</name>
		<pose>Unspecified</pose>
		<truncated>0</truncated>
		<difficult>0</difficult>
		<bndbox>
			<xmin>260</xmin>
			<ymin>152</ymin>
			<xmax>266</xmax>
			<ymax>166</ymax>
		</bndbox>
	</object>
	<object>
		<name>pedestrian</name>
		<pose>Unspecified</pose>
		<truncated>0</truncated>
		<difficult>0</difficult>
		<bndbox>
			<xmin>322</xmin>
			<ymin>181</ymin>
			<xmax>340</xmax>
			<ymax>216</ymax>
		</bndbox>
	</object>
</annotation>
