<annotation>
	<folder>imagesRaw</folder>
	<filename>2017-12-16 14:38:41.922495.jpg</filename>
	<path>/Users/abell/Development/other.nyc/Camera/imagesRaw/2017-12-16 14:38:41.922495.jpg</path>
	<source>
		<database>Unknown</database>
	</source>
	<size>
		<width>352</width>
		<height>240</height>
		<depth>3</depth>
	</size>
	<segmented>0</segmented>
	<object>
		<name>bus</name>
		<pose>Unspecified</pose>
		<truncated>0</truncated>
		<difficult>0</difficult>
		<bndbox>
			<xmin>158</xmin>
			<ymin>138</ymin>
			<xmax>200</xmax>
			<ymax>194</ymax>
		</bndbox>
	</object>
	<object>
		<name>police</name>
		<pose>Unspecified</pose>
		<truncated>0</truncated>
		<difficult>0</difficult>
		<bndbox>
			<xmin>215</xmin>
			<ymin>182</ymin>
			<xmax>275</xmax>
			<ymax>232</ymax>
		</bndbox>
	</object>
	<object>
		<name>car</name>
		<pose>Unspecified</pose>
		<truncated>0</truncated>
		<difficult>0</difficult>
		<bndbox>
			<xmin>121</xmin>
			<ymin>136</ymin>
			<xmax>137</xmax>
			<ymax>149</ymax>
		</bndbox>
	</object>
</annotation>
