<annotation>
	<folder>imagesRaw</folder>
	<filename>2017-12-18 23:54:12.266497.jpg</filename>
	<path>/Users/abell/Development/other.nyc/Camera/imagesRaw/2017-12-18 23:54:12.266497.jpg</path>
	<source>
		<database>Unknown</database>
	</source>
	<size>
		<width>352</width>
		<height>240</height>
		<depth>1</depth>
	</size>
	<segmented>0</segmented>
	<object>
		<name>bus</name>
		<pose>Unspecified</pose>
		<truncated>0</truncated>
		<difficult>0</difficult>
		<bndbox>
			<xmin>84</xmin>
			<ymin>140</ymin>
			<xmax>136</xmax>
			<ymax>199</ymax>
		</bndbox>
	</object>
	<object>
		<name>police</name>
		<pose>Unspecified</pose>
		<truncated>0</truncated>
		<difficult>0</difficult>
		<bndbox>
			<xmin>238</xmin>
			<ymin>214</ymin>
			<xmax>314</xmax>
			<ymax>239</ymax>
		</bndbox>
	</object>
</annotation>
