<annotation>
	<folder>imagesRaw</folder>
	<filename>2017-12-19 14:53:41.757168.jpg</filename>
	<path>/Users/abell/Development/other.nyc/Camera/imagesRaw/2017-12-19 14:53:41.757168.jpg</path>
	<source>
		<database>Unknown</database>
	</source>
	<size>
		<width>352</width>
		<height>240</height>
		<depth>3</depth>
	</size>
	<segmented>0</segmented>
	<object>
		<name>bus</name>
		<pose>Unspecified</pose>
		<truncated>0</truncated>
		<difficult>0</difficult>
		<bndbox>
			<xmin>157</xmin>
			<ymin>139</ymin>
			<xmax>201</xmax>
			<ymax>194</ymax>
		</bndbox>
	</object>
	<object>
		<name>car</name>
		<pose>Unspecified</pose>
		<truncated>0</truncated>
		<difficult>0</difficult>
		<bndbox>
			<xmin>60</xmin>
			<ymin>203</ymin>
			<xmax>118</xmax>
			<ymax>238</ymax>
		</bndbox>
	</object>
	<object>
		<name>car</name>
		<pose>Unspecified</pose>
		<truncated>0</truncated>
		<difficult>0</difficult>
		<bndbox>
			<xmin>52</xmin>
			<ymin>163</ymin>
			<xmax>86</xmax>
			<ymax>184</ymax>
		</bndbox>
	</object>
	<object>
		<name>car</name>
		<pose>Unspecified</pose>
		<truncated>0</truncated>
		<difficult>0</difficult>
		<bndbox>
			<xmin>201</xmin>
			<ymin>147</ymin>
			<xmax>221</xmax>
			<ymax>161</ymax>
		</bndbox>
	</object>
	<object>
		<name>pedestrian</name>
		<pose>Unspecified</pose>
		<truncated>0</truncated>
		<difficult>0</difficult>
		<bndbox>
			<xmin>252</xmin>
			<ymin>159</ymin>
			<xmax>261</xmax>
			<ymax>181</ymax>
		</bndbox>
	</object>
</annotation>
